setup.py
rxclass.egg-info/PKG-INFO
rxclass.egg-info/SOURCES.txt
rxclass.egg-info/dependency_links.txt
rxclass.egg-info/top_level.txt
rxclass_api/RxAPIWrapper.py
rxclass_api/RxClassHelpers.py
rxclass_api/__init__.py