Metadata-Version: 1.0
Name: rxclass
Version: 0.1.1
Summary: Python wrapper for RxClass API
Home-page: https://github.com/Ianphorsman/RxClassAPIWrapper
Author: Ian Horsman
Author-email: ianphorsman@gmail.com
License: MIT
Platform: UNKNOWN
